TOPSIS/__init__.py
TOPSIS/__main__.py
Rishabh_Gupta-1.0.0.dist-info/METADATA
Rishabh_Gupta-1.0.0.dist-info/WHEEL
Rishabh_Gupta-1.0.0.dist-info/entry_points.txt
Rishabh_Gupta-1.0.0.dist-info/license.txt
Rishabh_Gupta-1.0.0.dist-info/top_level.txt
Rishabh_Gupta-1.0.0.dist-info/RECORD
